pycaching/__init__.py
pycaching/cache.py
pycaching/errors.py
pycaching/geo.py
pycaching/geocaching.py
pycaching/log.py
pycaching/trackable.py
pycaching/util.py
pycaching-4.4.3.dist-info/LICENSE.txt
pycaching-4.4.3.dist-info/WHEEL
pycaching-4.4.3.dist-info/METADATA
pycaching-4.4.3.dist-info/RECORD
