Metadata-Version: 2.3
Name: pycaching
Version: 4.4.3
Summary: Geocaching.com site crawler. Provides tools for searching, fetching caches and geocoding.
Keywords: geocaching,crawler,geocache,cache,search,geocode,travelbug
Author-email: Tomas Bedrich <ja@tbedrich.cz>
Requires-Python: >= 3.5
Classifier: License :: OSI Approved :: GNU Lesser General Public License v3 (LGPLv3)
Classifier: Programming Language :: Python :: 3
Requires-Dist: requests ~= 2.8
Requires-Dist: urllib3 ~= 1.26
Requires-Dist: beautifulsoup4 ~= 4.9
Requires-Dist: geopy ~= 2.2.0
Requires-Dist: pytest ~= 8.2.1 ; extra == "dev"
Requires-Dist: pytest-cov ~= 3.0 ; extra == "dev"
Requires-Dist: betamax ~= 0.8 ; extra == "dev"
Requires-Dist: betamax-serializers ~= 0.2 ; extra == "dev"
Requires-Dist: black ~= 24.4.2 ; extra == "dev"
Requires-Dist: flake8 ~= 7.0 ; extra == "dev"
Requires-Dist: isort ~= 5.13.2 ; extra == "dev"
Requires-Dist: sphinx >= 3.5.4 ; extra == "docs"
Requires-Dist: sphinx-rtd-theme >= 1.1.1 ; extra == "docs"
Project-URL: Documentation, https://pycaching.readthedocs.io/
Project-URL: Source, https://github.com/tomasbedrich/pycaching
Provides-Extra: dev
Provides-Extra: docs
